{
	"modEnabled": true,
	"enabledOnGameLoad": true,
	"debug": false,
	"blockHoveringEnabled": false,
	"blockHoveringBoxThickness": 1.0,
	"blockHoveringColor": -1,
	"blockHoveringColorGradientEnabled": false,
	"blockHoveringColorGradient": -1,
	"blockHoveringFilledHitbox": false,
	"blockHoveringRainbow": false,
	"team1": [],
	"team1Color": -1,
	"team1ColorGradientEnabled": false,
	"team1ColorGradient": -1,
	"team2": [],
	"team2Color": -1,
	"team2ColorGradientEnabled": false,
	"team2ColorGradient": -1,
	"team3": [],
	"team3Color": -1,
	"team3ColorGradientEnabled": false,
	"team3ColorGradient": -1,
	"team4": [],
	"team4Color": -1,
	"team4ColorGradientEnabled": false,
	"team4ColorGradient": -1,
	"team5": [],
	"team5Color": -1,
	"team5ColorGradientEnabled": false,
	"team5ColorGradient": -1,
	"renderProjectiles": false,
	"recolorProjectiles": false,
	"profiles": {
		"default": {
			"PLAYER": {
				"should_render": false,
				"render_look_vector": false,
				"server_side_render": false,
				"color": -1,
				"color_gradient_enabled": false,
				"color_gradient": -1,
				"box_thickness": 1.0,
				"vanish_when_close": false,
				"vanish_fade": false,
				"vanish_distance": 5.0,
				"filled_hitbox": false,
				"change_color_on_damage_tick": false,
				"damage_tick_color": -1,
				"change_color_when_close": false,
				"close_color": -1,
				"close_distance": 5.0,
				"rainbow": false,
				"elytra_always_render": false
			},
			"END_CRYSTAL": {
				"should_render": false,
				"render_look_vector": false,
				"server_side_render": false,
				"color": -1,
				"color_gradient_enabled": false,
				"color_gradient": -1,
				"box_thickness": 1.0,
				"vanish_when_close": false,
				"vanish_fade": false,
				"vanish_distance": 5.0,
				"filled_hitbox": false,
				"change_color_on_damage_tick": false,
				"damage_tick_color": -1,
				"change_color_when_close": false,
				"close_color": -1,
				"close_distance": 5.0,
				"rainbow": false,
				"elytra_always_render": false
			},
			"PROJECTILE": {
				"should_render": false,
				"render_look_vector": false,
				"server_side_render": false,
				"color": -1,
				"color_gradient_enabled": false,
				"color_gradient": -1,
				"box_thickness": 1.0,
				"vanish_when_close": false,
				"vanish_fade": false,
				"vanish_distance": 5.0,
				"filled_hitbox": false,
				"change_color_on_damage_tick": false,
				"damage_tick_color": -1,
				"change_color_when_close": false,
				"close_color": -1,
				"close_distance": 5.0,
				"rainbow": false,
				"elytra_always_render": false
			},
			"ENDER_PEARL": {
				"should_render": false,
				"render_look_vector": false,
				"server_side_render": false,
				"color": -1,
				"color_gradient_enabled": false,
				"color_gradient": -1,
				"box_thickness": 1.0,
				"vanish_when_close": false,
				"vanish_fade": false,
				"vanish_distance": 5.0,
				"filled_hitbox": false,
				"change_color_on_damage_tick": false,
				"damage_tick_color": -1,
				"change_color_when_close": false,
				"close_color": -1,
				"close_distance": 5.0,
				"rainbow": false,
				"elytra_always_render": false
			},
			"HOSTILE_MOB": {
				"should_render": false,
				"render_look_vector": false,
				"server_side_render": false,
				"color": -1,
				"color_gradient_enabled": false,
				"color_gradient": -1,
				"box_thickness": 1.0,
				"vanish_when_close": false,
				"vanish_fade": false,
				"vanish_distance": 5.0,
				"filled_hitbox": false,
				"change_color_on_damage_tick": false,
				"damage_tick_color": -1,
				"change_color_when_close": false,
				"close_color": -1,
				"close_distance": 5.0,
				"rainbow": false,
				"elytra_always_render": false
			},
			"PASSIVE_MOB": {
				"should_render": false,
				"render_look_vector": false,
				"server_side_render": false,
				"color": -1,
				"color_gradient_enabled": false,
				"color_gradient": -1,
				"box_thickness": 1.0,
				"vanish_when_close": false,
				"vanish_fade": false,
				"vanish_distance": 5.0,
				"filled_hitbox": false,
				"change_color_on_damage_tick": false,
				"damage_tick_color": -1,
				"change_color_when_close": false,
				"close_color": -1,
				"close_distance": 5.0,
				"rainbow": false,
				"elytra_always_render": false
			},
			"ANGERABLE_MOB": {
				"should_render": false,
				"render_look_vector": false,
				"server_side_render": false,
				"color": -1,
				"color_gradient_enabled": false,
				"color_gradient": -1,
				"box_thickness": 1.0,
				"vanish_when_close": false,
				"vanish_fade": false,
				"vanish_distance": 5.0,
				"filled_hitbox": false,
				"change_color_on_damage_tick": false,
				"damage_tick_color": -1,
				"change_color_when_close": false,
				"close_color": -1,
				"close_distance": 5.0,
				"rainbow": false,
				"elytra_always_render": false
			},
			"BLOCK_ENTITY": {
				"should_render": false,
				"render_look_vector": false,
				"server_side_render": false,
				"color": -1,
				"color_gradient_enabled": false,
				"color_gradient": -1,
				"box_thickness": 1.0,
				"vanish_when_close": false,
				"vanish_fade": false,
				"vanish_distance": 5.0,
				"filled_hitbox": false,
				"change_color_on_damage_tick": false,
				"damage_tick_color": -1,
				"change_color_when_close": false,
				"close_color": -1,
				"close_distance": 5.0,
				"rainbow": false,
				"elytra_always_render": false
			},
			"ITEM": {
				"should_render": false,
				"render_look_vector": false,
				"server_side_render": false,
				"color": -1,
				"color_gradient_enabled": false,
				"color_gradient": -1,
				"box_thickness": 1.0,
				"vanish_when_close": false,
				"vanish_fade": false,
				"vanish_distance": 5.0,
				"filled_hitbox": false,
				"change_color_on_damage_tick": false,
				"damage_tick_color": -1,
				"change_color_when_close": false,
				"close_color": -1,
				"close_distance": 5.0,
				"rainbow": false,
				"elytra_always_render": false
			},
			"OTHER": {
				"should_render": false,
				"render_look_vector": false,
				"server_side_render": false,
				"color": -1,
				"color_gradient_enabled": false,
				"color_gradient": -1,
				"box_thickness": 1.0,
				"vanish_when_close": false,
				"vanish_fade": false,
				"vanish_distance": 5.0,
				"filled_hitbox": false,
				"change_color_on_damage_tick": false,
				"damage_tick_color": -1,
				"change_color_when_close": false,
				"close_color": -1,
				"close_distance": 5.0,
				"rainbow": false,
				"elytra_always_render": false
			}
		}
	},
	"currentProfile": "default",
	"profileToDelete": ""
}
